README.md
setup.py
ruko/__init__.py
ruko/binary_socket.py
ruko/command.py
ruko/context.py
ruko/empty_type.py
ruko/rdict.py
ruko/ruko_client.py
ruko/serialize.py
ruko/utils.py
ruko.egg-info/PKG-INFO
ruko.egg-info/SOURCES.txt
ruko.egg-info/dependency_links.txt
ruko.egg-info/top_level.txt